sklearn_plus/__init__.py
sklearn_plus/base.py
sklearn_plus/natural_language_processing/__init__.py
sklearn_plus/natural_language_processing/text_classification/__init__.py
sklearn_plus/natural_language_processing/text_classification/base.py
sklearn_plus/natural_language_processing/text_classification/model_fn/__init__.py
sklearn_plus/natural_language_processing/text_classification/model_fn/text_cnn.py
sklearn_plus/utils/__init__.py
sklearn_plus/utils/const.py
sklearn_plus/utils/data_helpers.py
sklearn_plus/utils/embedding.py
sklearn_plus-0.0.5.dist-info/DESCRIPTION.rst
sklearn_plus-0.0.5.dist-info/METADATA
sklearn_plus-0.0.5.dist-info/RECORD
sklearn_plus-0.0.5.dist-info/WHEEL
sklearn_plus-0.0.5.dist-info/metadata.json
sklearn_plus-0.0.5.dist-info/top_level.txt
