Metadata-Version: 2.0
Name: sklearn-plus
Version: 0.0.5
Summary: A set of python modules for Natural Language Processing
Home-page: https://github.com/ybbaigo/sklearn-plus
Author: Yuwen Yan
Author-email: ybbaigo@gmail.com
License: MIT license
Keywords: sklearn_plus
Platform: UNKNOWN
Classifier: Development Status :: 2 - Pre-Alpha
Classifier: Intended Audience :: Developers
Classifier: License :: OSI Approved :: MIT License
Classifier: Natural Language :: English
Classifier: Programming Language :: Python :: 2
Classifier: Programming Language :: Python :: 2.7
Classifier: Programming Language :: Python :: 3
Classifier: Programming Language :: Python :: 3.5
Classifier: Programming Language :: Python :: 3.6
Requires-Dist: dill
Requires-Dist: ipython (==5)
Requires-Dist: jieba
Requires-Dist: nltk
Requires-Dist: numpy
Requires-Dist: numpy (>=1.11.0)
Requires-Dist: pandas
Requires-Dist: scikit-learn
Requires-Dist: scipy
Requires-Dist: tensorflow (>=1.2.0)
